PyESPER/__init__.py
PyESPER/adjust_pH_DIC.py
PyESPER/coefs_AAinds.py
PyESPER/defaults.py
PyESPER/define_polygons.py
PyESPER/emlr_estimate.py
PyESPER/emlr_nn.py
PyESPER/errors.py
PyESPER/fetch_data.py
PyESPER/fetch_polys_NN.py
PyESPER/final_formatting.py
PyESPER/input_AAinds.py
PyESPER/inputdata_organize.py
PyESPER/interpolate.py
PyESPER/iterations.py
PyESPER/lir.py
PyESPER/lir_uncertainties.py
PyESPER/mixed.py
PyESPER/nn.py
PyESPER/organize_data.py
PyESPER/organize_nn_output.py
PyESPER/pH_DIC_nn_adjustment.py
PyESPER/pH_adjcalc.py
PyESPER/pH_adjustment.py
PyESPER/process_netresults.py
PyESPER/run_nets.py
PyESPER/simplecantestimatelr.py
PyESPER/temperature_define.py
pyesper-1.0.2.dist-info/METADATA
pyesper-1.0.2.dist-info/WHEEL
pyesper-1.0.2.dist-info/entry_points.txt
pyesper-1.0.2.dist-info/top_level.txt
pyesper-1.0.2.dist-info/RECORD
