Metadata-Version: 2.4
Name: PyESPER
Version: 1.0.2
Summary: Python version of ESPERv1
Author: LMD
Author-email: lmdias@uw.edu
Requires-Dist: numpy
Requires-Dist: seawater
Requires-Dist: scipy
Requires-Dist: matplotlib
Requires-Dist: PyCO2SYS
Requires-Dist: pandas
Dynamic: author
Dynamic: author-email
Dynamic: description
Dynamic: description-content-type
Dynamic: requires-dist
Dynamic: summary
